<Ui xmlns="http://www.blizzard.com/wow/ui/">
	<Script file="Previous\6.08.lua"/>
	<Script file="Previous\6.09.lua"/>
	<Script file="Previous\6.10.lua"/>
	<Script file="Previous\6.11.lua"/>
	<Script file="Previous\6.12.lua"/>
	<Script file="Previous\6.13.lua"/>
	<Script file="Previous\6.14.lua"/>
	<Script file="Previous\6.15.lua"/>
	<Script file="Previous\6.16.lua"/>
	<Script file="Previous\6.17.lua"/>
	<Script file="Previous\6.19.lua"/>
	<Script file="Previous\6.20.lua"/>
	<Script file="Previous\6.21.lua"/>
	<Script file="Previous\6.22.lua"/>
	<Script file="Previous\6.23.lua"/>
	<Script file="Previous\6.24.lua"/>
	<Script file="Previous\6.25.lua"/>
	<Script file="Previous\6.26.lua"/>
	<Script file="6.27.lua"/>
</Ui>
